{
  "task_id": "task_3",
  "hypothesis_id": "hyp_3_strong_feature_redundancy_pairs",
  "status": "completed",
  "findings": [
    "Multiple feature pairs in the cluster show perfect or near-perfect correlation, confirming strong redundancy.",
    "'Fwd Header Length' is low-cardinality and near-constant, reducing effective feature dimensionality.",
    "Local label-topology consistency checks reveal conflicts, indicating unstable dependencies around redundant features.",
    "Dependency profiles are not narrowly concentrated, suggesting redundancy impacts dependency stability broadly."
  ],
  "evidence_refs": [
    "task_3_step_03",
    "task_3_step_05",
    "task_3_step_07"
  ],
  "contradictions": [
    "High label neighborhood conflicts and duplicate label conflicts around 'Fwd Header Length' indicate local contradictions in dependency stability."
  ],
  "limitations": [
    "Analysis limited to features within the provided local dependency cluster; broader dataset effects not assessed."
  ]
}